wsp_jacquard/__init__.py
wsp_jacquard/_version.py
wsp_jacquard/api.py
wsp_jacquard/exceptions.py
wsp_jacquard/jacquard.py
wsp_jacquard-2.0.0.dist-info/LICENSE
wsp_jacquard-2.0.0.dist-info/METADATA
wsp_jacquard-2.0.0.dist-info/WHEEL
wsp_jacquard-2.0.0.dist-info/top_level.txt
wsp_jacquard-2.0.0.dist-info/RECORD
