Metadata-Version: 2.1
Name: wsp-jacquard
Version: 2.0.0
Summary: JSON-based configuration handler for models
Author-email: Brian Cheung <brian.cheung@wsp.com>
Project-URL: Homepage, https://github.com/wsp-sag/wsp-jacquard
Project-URL: Issues, https://github.com/wsp-sag/wsp-jacquard/issues
Classifier: Development Status :: 5 - Production/Stable
Classifier: License :: OSI Approved :: MIT License
Classifier: Operating System :: OS Independent
Classifier: Programming Language :: Python :: 3
Requires-Python: >=3.7
License-File: LICENSE
